memory_lake_sdk/__init__.py
memory_lake_sdk/client.py
memory_lake_sdk/exceptions.py
memory_lake_sdk/memory_backend.py
memory_lake_sdk/memory_tool.py
memory_lake_sdk/examples/README.md
memory_lake_sdk/examples/__init__.py
memory_lake_sdk/examples/basic_chat.py
memory_lake_sdk/examples/custom_backend.py
memory_lake_sdk/examples/manage_memory.py
memory_lake_sdk/examples/print_model.py
memory_lake_sdk-0.3.0.dist-info/licenses/LICENSE
memory_lake_sdk-0.3.0.dist-info/METADATA
memory_lake_sdk-0.3.0.dist-info/WHEEL
memory_lake_sdk-0.3.0.dist-info/entry_points.txt
memory_lake_sdk-0.3.0.dist-info/top_level.txt
memory_lake_sdk-0.3.0.dist-info/RECORD
