Metadata-Version: 2.4
Name: memory-lake-sdk
Version: 0.3.0
Summary: 简化开发者对 Claude Memory Tool 使用的 Python SDK
Home-page: https://github.com/memorylake/memory-lake-sdk
Author: Memory Lake Team
Author-email: Memory Lake Team <team@memorylake.ai>
Maintainer-email: Memory Lake Team <team@memorylake.ai>
License: MIT License
Project-URL: Homepage, https://github.com/memorylake/memory-lake-sdk
Project-URL: Documentation, https://github.com/memorylake/memory-lake-sdk/docs
Project-URL: Repository, https://github.com/memorylake/memory-lake-sdk
Project-URL: Bug Tracker, https://github.com/memorylake/memory-lake-sdk/issues
Project-URL: Changelog, https://github.com/memorylake/memory-lake-sdk/blob/main/CHANGELOG.md
Keywords: claude,anthropic,ai,memory,sdk,chatbot,conversation,context,python
Classifier: Development Status :: 3 - Alpha
Classifier: Intended Audience :: Developers
Classifier: License :: OSI Approved :: MIT License
Classifier: Operating System :: OS Independent
Classifier: Programming Language :: Python :: 3
Classifier: Programming Language :: Python :: 3.8
Classifier: Programming Language :: Python :: 3.9
Classifier: Programming Language :: Python :: 3.10
Classifier: Programming Language :: Python :: 3.11
Classifier: Programming Language :: Python :: 3.12
Classifier: Topic :: Software Development :: Libraries :: Python Modules
Classifier: Topic :: Scientific/Engineering :: Artificial Intelligence
Classifier: Topic :: Internet :: WWW/HTTP :: Dynamic Content
Requires-Python: >=3.8
License-File: LICENSE
Requires-Dist: anthropic>=0.39.0
Provides-Extra: dev
Requires-Dist: pytest>=7.0.0; extra == "dev"
Requires-Dist: pytest-cov>=4.0.0; extra == "dev"
Requires-Dist: black>=22.0.0; extra == "dev"
Requires-Dist: flake8>=5.0.0; extra == "dev"
Requires-Dist: mypy>=1.0.0; extra == "dev"
Requires-Dist: pre-commit>=2.20.0; extra == "dev"
Provides-Extra: docs
Requires-Dist: sphinx>=5.0.0; extra == "docs"
Requires-Dist: sphinx-rtd-theme>=1.0.0; extra == "docs"
Requires-Dist: myst-parser>=0.18.0; extra == "docs"
Provides-Extra: test
Requires-Dist: pytest>=7.0.0; extra == "test"
Requires-Dist: pytest-cov>=4.0.0; extra == "test"
Requires-Dist: pytest-mock>=3.8.0; extra == "test"
Dynamic: author
Dynamic: home-page
Dynamic: license-file
Dynamic: requires-python
